ml_metadata/version.py
ml_metadata/py.typed
ml_metadata/__init__.py
ml_metadata/errors.py
ml_metadata/proto/metadata_store_service_pb2.py
ml_metadata/proto/metadata_store_service_pb2_grpc.py
ml_metadata/proto/metadata_store_pb2.py
ml_metadata/proto/__init__.py
ml_metadata/tools/__init__.py
ml_metadata/metadata_store/metadata_store_test.py
ml_metadata/metadata_store/metadata_store.py
ml_metadata/metadata_store/mlmd_types.py
ml_metadata/metadata_store/mlmd_types_test.py
ml_metadata/metadata_store/conftest.py
ml_metadata/metadata_store/__init__.py
ml_metadata/metadata_store/pywrap/metadata_store_extension.so
ml_metadata/metadata_store/pywrap/__init__.py
ml_metadata/simple_types/__init__.py
ml_metadata/simple_types/proto/__init__.py
ml_metadata/simple_types/proto/simple_types_pb2.py
ml_metadata_czgdp1807-1.18.0.dev0.dist-info/LICENSE
ml_metadata_czgdp1807-1.18.0.dev0.dist-info/WHEEL
ml_metadata_czgdp1807-1.18.0.dev0.dist-info/top_level.txt
ml_metadata_czgdp1807-1.18.0.dev0.dist-info/namespace_packages.txt
ml_metadata_czgdp1807-1.18.0.dev0.dist-info/METADATA
ml_metadata_czgdp1807-1.18.0.dev0.dist-info/RECORD
