Metadata-Version: 2.1
Name: ml-metadata-czgdp1807
Version: 1.18.0.dev0
Summary: A library for maintaining metadata for artifacts.
Home-page: https://github.com/google/ml-metadata
Download-URL: https://github.com/google/ml-metadata/tags
Author: Google LLC
Author-email: tensorflow-extended-dev@googlegroups.com
License: Apache 2.0
Keywords: machine learning metadata tfx
Classifier: Development Status :: 5 - Production/Stable
Classifier: Intended Audience :: Developers
Classifier: Intended Audience :: Education
Classifier: Intended Audience :: Science/Research
Classifier: License :: OSI Approved :: Apache Software License
Classifier: Operating System :: MacOS :: MacOS X
Classifier: Operating System :: POSIX :: Linux
Classifier: Programming Language :: Python
Classifier: Programming Language :: Python :: 3
Classifier: Programming Language :: Python :: 3.9
Classifier: Programming Language :: Python :: 3.10
Classifier: Programming Language :: Python :: 3.11
Classifier: Programming Language :: Python :: 3 :: Only
Classifier: Topic :: Scientific/Engineering
Classifier: Topic :: Scientific/Engineering :: Artificial Intelligence
Classifier: Topic :: Scientific/Engineering :: Mathematics
Classifier: Topic :: Software Development
Classifier: Topic :: Software Development :: Libraries
Classifier: Topic :: Software Development :: Libraries :: Python Modules
Requires-Python: >=3.9,<4
License-File: LICENSE
Requires-Dist: absl-py<2.0.0,>=0.9
Requires-Dist: attrs<24,>=20.3
Requires-Dist: grpcio<2,>=1.8.6
Requires-Dist: protobuf<5,>=4.21.6
Requires-Dist: six<2,>=1.10
Provides-Extra: docs
Requires-Dist: mkdocs; extra == "docs"
Requires-Dist: mkdocs-material; extra == "docs"
Requires-Dist: mkdocstrings[python]; extra == "docs"
Requires-Dist: griffe-inherited-docstrings; extra == "docs"
Requires-Dist: mkdocs-autorefs; extra == "docs"
Requires-Dist: black; extra == "docs"
Requires-Dist: mkdocs-jupyter; extra == "docs"
Requires-Dist: mkdocs-caption; extra == "docs"
Provides-Extra: lint
Requires-Dist: pre-commit; extra == "lint"
